contextify/__init__.py
contextify/__main__.py
contextify/py.typed
contextify-0.0.1.dist-info/LICENSE
contextify-0.0.1.dist-info/METADATA
contextify-0.0.1.dist-info/WHEEL
contextify-0.0.1.dist-info/entry_points.txt
contextify-0.0.1.dist-info/RECORD
