Metadata-Version: 2.1
Name: contextify
Version: 0.0.1
Summary: Contextify
Home-page: https://github.com/56kyle/contextify
License: MIT
Author: Kyle Oliver
Author-email: 56kyleoliver@gmail.com
Requires-Python: >=3.9,<4.0
Classifier: Development Status :: 1 - Planning
Classifier: License :: OSI Approved :: MIT License
Classifier: Programming Language :: Python :: 3
Classifier: Programming Language :: Python :: 3.9
Classifier: Programming Language :: Python :: 3.10
Classifier: Programming Language :: Python :: 3.11
Requires-Dist: click (>=8.0.1)
Requires-Dist: loguru (>=0.7.2,<0.8.0)
Requires-Dist: platformdirs (>=4.2.2,<5.0.0)
Project-URL: Changelog, https://github.com/56kyle/contextify/releases
Project-URL: Documentation, https://contextify.readthedocs.io
Project-URL: Repository, https://github.com/56kyle/contextify
